{
  "project_info": {
    "project_number": "863788857384",
    "project_id": "climalert-a6a9e",
    "storage_bucket": "climalert-a6a9e.appspot.com"
  },
  "client": [
    {
      "client_info": {
        "mobilesdk_app_id": "1:863788857384:android:6d3eec16570e0e83c09d1d",
        "android_client_info": {
          "package_name": "com.example.climalert"
        }
      },
      "oauth_client": [
        {
          "client_id": "863788857384-40qq39n0gk9ep9bsvc14go6k1r7vkq96.apps.googleusercontent.com",
          "client_type": 1,
          "android_info": {
            "package_name": "com.example.climalert",
            "certificate_hash": "e4c991b0e05018813eca11a3c90c380b4424ebef"
          }
        },
        {
          "client_id": "863788857384-1fuvh34n2o9j8t92b0ips2u3ra57scgu.apps.googleusercontent.com",
          "client_type": 3
        }
      ],
      "api_key": [
        {
          "current_key": "AIzaSyCX5wcNtVEXKNSQzNwVB4_CGpiCTwT8oMM"
        }
      ],
      "services": {
        "appinvite_service": {
          "other_platform_oauth_client": [
            {
              "client_id": "863788857384-1fuvh34n2o9j8t92b0ips2u3ra57scgu.apps.googleusercontent.com",
              "client_type": 3
            }
          ]
        }
      }
    }
  ],
  "configuration_version": "1"
}